encoder_decoder_lib/__init__.py
encoder_decoder_lib/decoder.py
encoder_decoder_lib/encoder.py
encoder_decoder_lib/utils.py
encoder_decoder_lib/utlis.py
my_translation_package_deep_learning-0.1.5.dist-info/LICENSE
my_translation_package_deep_learning-0.1.5.dist-info/METADATA
my_translation_package_deep_learning-0.1.5.dist-info/WHEEL
my_translation_package_deep_learning-0.1.5.dist-info/top_level.txt
my_translation_package_deep_learning-0.1.5.dist-info/RECORD
