Metadata-Version: 2.1
Name: my_translation_package_deep_learning
Version: 0.1.5
Summary: A package for sequence-to-sequence models with encoder-decoder architecture
Home-page: https://github.com/Shivam909058/my_translation_package
Author: shivam singh
Author-email: shivamatvit@gmail.com
Classifier: Programming Language :: Python :: 3
Classifier: License :: OSI Approved :: MIT License
Classifier: Operating System :: OS Independent
Requires-Python: >=3.6
License-File: LICENSE
Requires-Dist: tensorflow
Requires-Dist: numpy
Requires-Dist: pandas
Requires-Dist: scikit-learn
Requires-Dist: matplotlib
